iamend_ci/__init__.py
iamend_ci/ax.py
iamend_ci/bo.py
iamend_ci/fit.py
iamend_ci/plt.py
iamend_ci/so.py
iamend_ci/theo.py
iamend_ci-0.0.3.dist-info/LICENSE
iamend_ci-0.0.3.dist-info/METADATA
iamend_ci-0.0.3.dist-info/WHEEL
iamend_ci-0.0.3.dist-info/top_level.txt
iamend_ci-0.0.3.dist-info/RECORD
