Metadata-Version: 2.1
Name: iamend-ci
Version: 0.0.3
Summary: Libreria para la estimacion de la permeabilidad relativa efectiva.
Home-page: https://github.com/carabedo/iamend_ci
Author: carabedo
Author-email: fernandocarabedo@cnea.gov.ar
License: UNKNOWN
Project-URL: Bug Tracker, https://github.com/carabedo/iamend_ci/issues
Platform: UNKNOWN
Classifier: Programming Language :: Python :: 3
Classifier: License :: OSI Approved :: MIT License
Classifier: Operating System :: OS Independent
Requires-Python: >=3.5
